mergesvvcf/__init__.py
mergesvvcf/locations.cpython-38-darwin.so
mergesvvcf/mergedfile.py
mergesvvcf/variantdict.cpython-38-darwin.so
mergesvvcf/vcftobreakpoints.cpython-38-darwin.so
mergesvvcf-1.0.3.dist-info/METADATA
mergesvvcf-1.0.3.dist-info/WHEEL
mergesvvcf-1.0.3.dist-info/entry_points.txt
mergesvvcf-1.0.3.dist-info/top_level.txt
mergesvvcf-1.0.3.dist-info/RECORD
